cdxjGenerator/__init__.py
cdxjGenerator/__main__.py
cdxjGenerator/cdxjGenerator.py
cdxjGenerator-0.0.1.dist-info/LICENSE
cdxjGenerator-0.0.1.dist-info/METADATA
cdxjGenerator-0.0.1.dist-info/WHEEL
cdxjGenerator-0.0.1.dist-info/entry_points.txt
cdxjGenerator-0.0.1.dist-info/top_level.txt
cdxjGenerator-0.0.1.dist-info/RECORD
