Metadata-Version: 2.1
Name: cdxjGenerator
Version: 0.0.1
Summary: Generate CDXJ TimeMaps for testing elsewhere
Home-page: https://github.com/machawk1/cdxjGenerator
Author: Mat Kelly
Author-email: me@matkelly.com
License: MIT
Download-URL: https://github.com/cdxjGenerator
Keywords: web archives replay cdxj memento
Platform: UNKNOWN
Classifier: Development Status :: 3 - Alpha
Classifier: Environment :: Web Environment
Classifier: Programming Language :: Python :: 3.7
Classifier: Programming Language :: Python :: 3.8
Classifier: License :: OSI Approved :: MIT License
Classifier: Intended Audience :: Developers
Classifier: Intended Audience :: Information Technology
Classifier: Intended Audience :: Science/Research
Classifier: Topic :: Internet :: WWW/HTTP
Classifier: Topic :: System :: Archiving
Classifier: Topic :: System :: Archiving :: Backup
Classifier: Topic :: System :: Archiving :: Mirroring
Classifier: Topic :: Utilities
Provides: cdxjGenerator
Requires-Dist: Faker
Requires-Dist: surt (>=0.3.0)
Requires-Dist: tlds
